[{"id":"0a0e2db2-1313-11ef-9108-426a4b393c84","tool":"Add","function":"addItems","functionParams":null,"userDefined":null,"group":null,"modal":null,"showOn":"~init,submit,cancel","tab":"Cars","index":5,"control":null,"ignore":null,"dateCreated":"2024-05-15 16:29:56.575","createdByUserId":null,"dateModified":null,"modifiedByUserId":null},
 {"id":"0a0efc2e-1313-11ef-9108-426a4b393c84","tool":"Edit","function":"editItems","functionParams":null,"userDefined":null,"group":null,"modal":null,"showOn":"~init,submit,cancel","tab":"Cars","index":10,"control":null,"ignore":null,"dateCreated":"2024-05-15 16:29:56.575","createdByUserId":null,"dateModified":null,"modifiedByUserId":null},
 {"id":"0a0f00d4-1313-11ef-9108-426a4b393c84","tool":"Delete","function":"deleteItems","functionParams":null,"userDefined":null,"group":null,"modal":null,"showOn":"~init,submit,cancel","tab":"Cars","index":15,"control":null,"ignore":null,"dateCreated":"2024-05-15 16:29:56.575","createdByUserId":null,"dateModified":null,"modifiedByUserId":null},
 {"id":"0a0f01d8-1313-11ef-9108-426a4b393c84","tool":"Submit","function":"submitItems","functionParams":null,"userDefined":null,"group":null,"modal":null,"showOn":"add,edit","tab":"Cars","index":20,"control":null,"ignore":null,"dateCreated":"2024-05-15 16:29:56.575","createdByUserId":null,"dateModified":null,"modifiedByUserId":null},
 {"id":"0a0f02aa-1313-11ef-9108-426a4b393c84","tool":"Cancel","function":"cancelItems","functionParams":null,"userDefined":null,"group":null,"modal":null,"showOn":"add,edit","tab":"Cars","index":25,"control":null,"ignore":null,"dateCreated":"2024-05-15 16:29:56.575","createdByUserId":null,"dateModified":null,"modifiedByUserId":null},
 {"id":"0a0f0372-1313-11ef-9108-426a4b393c84","tool":"Refresh","function":"refreshItems","functionParams":null,"userDefined":null,"group":null,"modal":null,"showOn":"~init,submit,cancel","tab":"Cars","index":30,"control":null,"ignore":null,"dateCreated":"2024-05-15 16:29:56.575","createdByUserId":null,"dateModified":null,"modifiedByUserId":null}]